aligned_py/abi/AlignedLayerServiceManager.json
aligned_py/abi/BatcherPaymentService.json
aligned_py/communication/batch.py
aligned_py/communication/messaging.py
aligned_py/communication/protocol.py
aligned_py/communication/serialization.py
aligned_py/core/constants.py
aligned_py/core/errors.py
aligned_py/core/types.py
aligned_py/eth/aligned_service_manager.py
aligned_py/eth/batcher_payment_service.py
aligned_py/sdk.py
aligned_py-0.1.2.dist-info/METADATA
aligned_py-0.1.2.dist-info/WHEEL
aligned_py-0.1.2.dist-info/RECORD
